README.rst
main.py
setup.py
readthecode.egg-info/PKG-INFO
readthecode.egg-info/SOURCES.txt
readthecode.egg-info/dependency_links.txt
readthecode.egg-info/entry_points.txt
readthecode.egg-info/top_level.txt