Metadata-Version: 1.1
Name: readthecode
Version: 0.1.4
Summary: You read the doc, now better read the code
Home-page: https://github.com/hvnsweeting/readthecode
Author: Viet Hung Nguyen
Author-email: hvn@familug.org
License: MIT
Platform: UNKNOWN
Classifier: Environment :: Console
